sevdy/__init__.py
sevdy/_init_.py
sevdy/cli.py
sevdy/core.py
sevdy-0.1.0.dist-info/licenses/LICENSE
sevdy-0.1.0.dist-info/METADATA
sevdy-0.1.0.dist-info/WHEEL
sevdy-0.1.0.dist-info/entry_points.txt
sevdy-0.1.0.dist-info/top_level.txt
sevdy-0.1.0.dist-info/RECORD
